onset/__init__.py
onset/__main__.py
onset-1.1.0.dist-info/LICENSE.txt
onset-1.1.0.dist-info/METADATA
onset-1.1.0.dist-info/WHEEL
onset-1.1.0.dist-info/entry_points.txt
onset-1.1.0.dist-info/top_level.txt
onset-1.1.0.dist-info/RECORD
