Metadata-Version: 2.1
Name: onset
Version: 1.1.0
Summary: Run set operations on files.
Home-page: https://github.com/fmind/onset
Author: Médéric Hurier (fmind)
Author-email: fmind@fmind.me
License: LGPL-3.0
Keywords: set file utility operation
Platform: UNKNOWN
Classifier: Development Status :: 4 - Beta
Requires-Python: >=3.7
